LICENSE.txt
MANIFEST.in
README.rst
setup.cfg
setup.py
async_thumbnail/__init__.py
async_thumbnail/middleware.py
async_thumbnail/urls.py
async_thumbnail/utils.py
async_thumbnail/views.py
async_thumbnail.egg-info/PKG-INFO
async_thumbnail.egg-info/SOURCES.txt
async_thumbnail.egg-info/dependency_links.txt
async_thumbnail.egg-info/not-zip-safe
async_thumbnail.egg-info/requires.txt
async_thumbnail.egg-info/top_level.txt
async_thumbnail/templatetags/__init__.py
async_thumbnail/templatetags/async_thumbnail.py
tests/__init__.py
tests/helpers.py
tests/test_middleware.py
tests/test_templatetags.py
tests/test_utils.py
tests/test_views.py