Metadata-Version: 1.1
Name: async-thumbnail
Version: 2.0
Summary: Offload sorl thumbnail rendering to a render view.
Home-page: https://gitlab.com/mediamoose/async-thumbnail/tree/v2.0
Author: Sven Groot (Mediamoose)
Author-email: sven@mediamoose.nl
License: MIT
Download-URL: https://gitlab.com/mediamoose/async-thumbnail/repository/v2.0/archive.tar.gz
Keywords: async,asynchronous,thumbnail,sorl,django
Platform: UNKNOWN
Classifier: Development Status :: 3 - Alpha
Classifier: Framework :: Django
Classifier: Framework :: Django :: 1.11
Classifier: Framework :: Django :: 2.0
Classifier: Framework :: Django :: 2.1
Classifier: Framework :: Django :: 2.2
Classifier: Intended Audience :: Developers
Classifier: License :: OSI Approved :: MIT License
Classifier: Natural Language :: English
Classifier: Operating System :: POSIX :: Linux
Classifier: Programming Language :: Python
Classifier: Programming Language :: Python :: 3.6
Classifier: Programming Language :: Python :: 3.7
